tfgen/__init__.py
tfgen/const.py
tfgen/observe_event_classes.py
tfgen/tfgen.py
tfgen/utils.py
tfgen/methods/__init__.py
tfgen/methods/base_method.py
tfgen/methods/classic.py
tfgen/methods/classic_large_sparse.py
tfgen/models/__init__.py
tfgen/models/tet.py
tfgen-0.6.1.dist-info/LICENSE
tfgen-0.6.1.dist-info/METADATA
tfgen-0.6.1.dist-info/WHEEL
tfgen-0.6.1.dist-info/top_level.txt
tfgen-0.6.1.dist-info/RECORD
