Metadata-Version: 2.1
Name: tfgen
Version: 0.6.1
Summary: Online Transition-Based Feature Generation for Anomaly Detection in Concurrent Data Streams.
Home-page: https://github.com/yinzheng-zhong/TFGen
Author: Yinzheng Zhong
Author-email: y.zhong10@liverpool.ac.uk
License: UNKNOWN
Keywords: anomaly detection,machine learning,intrusion detection,process mining
Platform: UNKNOWN
Classifier: Development Status :: 2 - Pre-Alpha
Classifier: License :: OSI Approved :: GNU General Public License v3 (GPLv3)
Classifier: Intended Audience :: Education
Classifier: Intended Audience :: Telecommunications Industry
Classifier: Intended Audience :: Science/Research
Classifier: Intended Audience :: Information Technology
License-File: LICENSE
Requires-Dist: pandas
Requires-Dist: numpy
Requires-Dist: scipy
